jupyterlab_tour/__init__.py
jupyterlab_tour/_version.py
jupyterlab_tour-4.0.1.data/data/share/jupyter/labextensions/jupyterlab-tour/package.json
jupyterlab_tour-4.0.1.data/data/share/jupyter/labextensions/jupyterlab-tour/schemas/jupyterlab-tour/package.json.orig
jupyterlab_tour-4.0.1.data/data/share/jupyter/labextensions/jupyterlab-tour/schemas/jupyterlab-tour/user-tours.json
jupyterlab_tour-4.0.1.data/data/share/jupyter/labextensions/jupyterlab-tour/static/380.3d757eec3a2d5c057e16.js
jupyterlab_tour-4.0.1.data/data/share/jupyter/labextensions/jupyterlab-tour/static/581.612c2a7787620c9c4321.js
jupyterlab_tour-4.0.1.data/data/share/jupyter/labextensions/jupyterlab-tour/static/581.612c2a7787620c9c4321.js.LICENSE.txt
jupyterlab_tour-4.0.1.data/data/share/jupyter/labextensions/jupyterlab-tour/static/651.49677b978dfcd6a17665.js
jupyterlab_tour-4.0.1.data/data/share/jupyter/labextensions/jupyterlab-tour/static/651.49677b978dfcd6a17665.js.LICENSE.txt
jupyterlab_tour-4.0.1.data/data/share/jupyter/labextensions/jupyterlab-tour/static/747.f0c82aefdf72cbeca462.js
jupyterlab_tour-4.0.1.data/data/share/jupyter/labextensions/jupyterlab-tour/static/remoteEntry.c48d7690a4adc05b4e31.js
jupyterlab_tour-4.0.1.data/data/share/jupyter/labextensions/jupyterlab-tour/static/style.js
jupyterlab_tour-4.0.1.data/data/share/jupyter/labextensions/jupyterlab-tour/static/third-party-licenses.json
jupyterlab_tour-4.0.1.data/data/share/jupyter/labextensions/jupyterlab-tour/install.json
jupyterlab_tour-4.0.1.dist-info/METADATA
jupyterlab_tour-4.0.1.dist-info/WHEEL
jupyterlab_tour-4.0.1.dist-info/licenses/LICENSE
jupyterlab_tour-4.0.1.dist-info/RECORD
