Metadata-Version: 2.1
Name: jupyterlab_tour
Version: 4.0.1
Summary: A JupyterLab UI Tour.
Project-URL: Homepage, https://github.com/jupyterlab-contrib/jupyterlab-tour
Project-URL: Bug Tracker, https://github.com/jupyterlab-contrib/jupyterlab-tour/issues
Project-URL: Repository, https://github.com/jupyterlab-contrib/jupyterlab-tour.git
Author-email: Frederic Collonval <fcollonval@gmail.com>
License: BSD 3-Clause License
License-File: LICENSE
Classifier: Framework :: Jupyter
Classifier: Framework :: Jupyter :: JupyterLab
Classifier: Framework :: Jupyter :: JupyterLab :: 3
Classifier: Framework :: Jupyter :: JupyterLab :: 4
Classifier: Framework :: Jupyter :: JupyterLab :: Extensions
Classifier: Framework :: Jupyter :: JupyterLab :: Extensions :: Prebuilt
Classifier: License :: OSI Approved :: BSD License
Classifier: Programming Language :: Python
Classifier: Programming Language :: Python :: 3
Classifier: Programming Language :: Python :: 3.8
Classifier: Programming Language :: Python :: 3.9
Classifier: Programming Language :: Python :: 3.10
Classifier: Programming Language :: Python :: 3.11
Requires-Python: >=3.8
